dcclog/__init__.py
dcclog/colors.py
dcclog/formatters.py
dcclog/handlers.py
dcclog/logger.py
dcclog/py.typed
dcclog/reader.py
dcclog/utils.py
dcclog/wrapper.py
dcclog/cipher/__init__.py
dcclog/cipher/aes.py
dcclog/cipher/chacha.py
dcclog/cipher/rsa.py
dcclog-0.10.0.dist-info/LICENSE
dcclog-0.10.0.dist-info/METADATA
dcclog-0.10.0.dist-info/WHEEL
dcclog-0.10.0.dist-info/entry_points.txt
dcclog-0.10.0.dist-info/top_level.txt
dcclog-0.10.0.dist-info/RECORD
