Metadata-Version: 2.1
Name: dcclog
Version: 0.10.0
Summary: Logging package with color and encryption support
Author-email: jamazi <jamazi@tutanota.com>
Project-URL: Homepage, https://github.com/jamazi/dcclog
Project-URL: Bug Tracker, https://github.com/jamazi/dcclog/issues
Keywords: log
Classifier: Programming Language :: Python :: 3
Classifier: License :: OSI Approved :: MIT License
Classifier: Operating System :: OS Independent
Requires-Python: >=3.9
License-File: LICENSE
Provides-Extra: all
Requires-Dist: dcclog[dev] ; extra == 'all'
Requires-Dist: dcclog[cipher] ; extra == 'all'
Provides-Extra: cipher
Requires-Dist: pycryptodome (>=3.15.0) ; extra == 'cipher'
Provides-Extra: dev
Requires-Dist: black ; extra == 'dev'
Requires-Dist: isort ; extra == 'dev'
Requires-Dist: mypy ; extra == 'dev'
Requires-Dist: pylint ; extra == 'dev'
Requires-Dist: pytest ; extra == 'dev'
